{"17": {"hour": 13, "wdays": [0], "minute": 55, "name": "b", "repeat": "no"}, "16": {"hour": 13, "wdays": [0], "minute": 51, "name": "a", "repeat": "no"}, "18": {"name": "a", "wdays": [0], "minute": 51, "hour": 13, "repeat": "no"}, "3": {"hour": 13, "wdays": [0], "minute": 55, "name": "b", "repeat": "no"}, "9": {"hour": 13, "wdays": [0], "minute": 55, "name": "b", "repeat": "no"}, "5": {"hour": 13, "wdays": [0], "minute": 55, "name": "b", "repeat": "no"}, "4": {"hour": 13, "wdays": [0], "minute": 51, "name": "a", "repeat": "no"}, "0": {"hour": 13, "wdays": [0], "minute": 51, "name": "a", "repeat": "no"}, "13": {"hour": 13, "wdays": [0], "minute": 55, "name": "b", "repeat": "no"}, "2": {"hour": 13, "wdays": [0], "minute": 51, "name": "a", "repeat": "no"}, "8": {"hour": 13, "wdays": [0], "minute": 51, "name": "a", "repeat": "no"}, "11": {"hour": 13, "wdays": [0], "minute": 55, "name": "b", "repeat": "no"}, "19": {"hour": 13, "wdays": [0], "minute": 55, "name": "b", "repeat": "no"}, "10": {"hour": 13, "wdays": [0], "minute": 51, "name": "a", "repeat": "no"}, "12": {"hour": 13, "wdays": [0], "minute": 51, "name": "a", "repeat": "no"}, "15": {"hour": 13, "wdays": [0], "minute": 55, "name": "b", "repeat": "no"}, "14": {"hour": 13, "wdays": [0], "minute": 51, "name": "a", "repeat": "no"}, "1": {"hour": 13, "wdays": [0], "minute": 55, "name": "b", "repeat": "no"}, "6": {"hour": 13, "wdays": [0], "minute": 51, "name": "a", "repeat": "no"}, "7": {"hour": 13, "wdays": [0], "minute": 55, "name": "b", "repeat": "no"}}